<?xml version="1.0" encoding="UTF-8"?>
<nuds xmlns:xsi="http://www.w3.org/2001/XMLSchema-instance"
	xsi:schemaLocation="http://nomisma.org/nuds http://nomisma.org/nuds.xsd"
	xmlns="http://nomisma.org/nuds" xmlns:mets="http://www.loc.gov/METS/"
	xmlns:gml="http://www.opengis.net/gml" xmlns:tei="http://www.tei-c.org/ns/1.0"
	xmlns:xlink="http://www.w3.org/1999/xlink" recordType="physical">
	<control>
		<recordId>asinanmd1</recordId>
		<publicationStatus>approved</publicationStatus>
		<maintenanceStatus>new</maintenanceStatus>
		<maintenanceAgency>
			<agencyName>University of Warwick</agencyName>
		</maintenanceAgency>
		<maintenanceHistory>
			<maintenanceEvent>
				<eventType>created</eventType>
				<eventDateTime standardDateTime="2018-07-11T18:51:04.396+01:00"/>
				<agentType>human</agentType>
				<agent>admin</agent>
			</maintenanceEvent>
		</maintenanceHistory>
		<rightsStmt>
			<copyrightHolder>University of Warwick</copyrightHolder>
			<license xlink:type="simple" xlink:href="http://opendatacommons.org/licenses/odbl/"/>
		</rightsStmt>
		<semanticDeclaration>
			<prefix>nmo</prefix>
			<namespace>http://nomisma.org/ontology#</namespace>
		</semanticDeclaration>
	</control>
	<descMeta>
		<title xml:lang="en">National Museum of Denmark 1</title>
		<physDesc>
			<shape>Circle</shape>
			<measurementsSet>
				<weight units="g">15</weight>
			</measurementsSet>
		</physDesc>
		<typeDesc xlink:href="https://coins.warwick.ac.uk/token-types/id/alfoeldi_asina8"> </typeDesc>
		<adminDesc>
			<collection>National Museum of Denmark</collection>
		</adminDesc>
		<noteSet>
			<note>A. Alföldi (1951) considered this specimen as belonging to the Asina series, but
				this is uncertain.</note>
		</noteSet>
	</descMeta>
</nuds>
